{
  "employeeData": [
    {
      "id": 101,
      "title": "emp-1",
      "designation": "Jr Dev",
      "exp": 4
    },
    {
      "id": 102,
      "title": "emp-2",
      "designation": "Sr Dev",
      "exp": 10
    },
    {
      "id": 103,
      "title": "emp-3",
      "designation": "Tester",
      "exp": 11
    },
    {
      "id": 104,
      "title": "emp-4",
      "designation": "Tech Manager",
      "exp": 10
    },
    {
      "id": 105,
      "title": "emp-5",
      "designation": "Sr Tester",
      "exp": 15
    }
  ]
}